Metadata-Version: 1.1
Name: imreplace
Version: 0.0.1
Summary: Replace A Value in Immutable Data
Home-page: UNKNOWN
Author: HARI PRASANTH S
Author-email: hariprasanth581@gmail.com
License: MIT
Keywords: Replace,Immutable,Tuple,String
Platform: UNKNOWN
Classifier: Development Status :: 5 - Production/Stable
Classifier: Intended Audience :: Education
Classifier: Operating System :: Microsoft :: Windows :: Windows 10
Classifier: License :: OSI Approved :: MIT License
Classifier: Programming Language :: Python :: 3
